wl_magixx/__init__.py
wl_magixx/discordbot/__init__.py
wl_magixx/discordbot/cogs/whitelist.py
whitelist_roblox-0.1.9.dist-info/METADATA
whitelist_roblox-0.1.9.dist-info/WHEEL
whitelist_roblox-0.1.9.dist-info/top_level.txt
whitelist_roblox-0.1.9.dist-info/RECORD
